helloworld.py
helloworld_praalinepy-0.0.1.dist-info/LICENSE.txt
helloworld_praalinepy-0.0.1.dist-info/METADATA
helloworld_praalinepy-0.0.1.dist-info/WHEEL
helloworld_praalinepy-0.0.1.dist-info/top_level.txt
helloworld_praalinepy-0.0.1.dist-info/RECORD
